google-stubs/api/__init__.pyi
google-stubs/api/annotations_pb2.pyi
google-stubs/api/auth_pb2.pyi
google-stubs/api/backend_pb2.pyi
google-stubs/api/billing_pb2.pyi
google-stubs/api/client_pb2.pyi
google-stubs/api/config_change_pb2.pyi
google-stubs/api/consumer_pb2.pyi
google-stubs/api/context_pb2.pyi
google-stubs/api/control_pb2.pyi
google-stubs/api/distribution_pb2.pyi
google-stubs/api/documentation_pb2.pyi
google-stubs/api/endpoint_pb2.pyi
google-stubs/api/error_reason_pb2.pyi
google-stubs/api/field_behavior_pb2.pyi
google-stubs/api/field_info_pb2.pyi
google-stubs/api/http_pb2.pyi
google-stubs/api/httpbody_pb2.pyi
google-stubs/api/label_pb2.pyi
google-stubs/api/launch_stage_pb2.pyi
google-stubs/api/log_pb2.pyi
google-stubs/api/logging_pb2.pyi
google-stubs/api/metric_pb2.pyi
google-stubs/api/monitored_resource_pb2.pyi
google-stubs/api/monitoring_pb2.pyi
google-stubs/api/policy_pb2.pyi
google-stubs/api/py.typed
google-stubs/api/quota_pb2.pyi
google-stubs/api/resource_pb2.pyi
google-stubs/api/routing_pb2.pyi
google-stubs/api/service_pb2.pyi
google-stubs/api/source_info_pb2.pyi
google-stubs/api/system_parameter_pb2.pyi
google-stubs/api/usage_pb2.pyi
google-stubs/api/visibility_pb2.pyi
google-stubs/cloud/extended_operations_pb2.pyi
google-stubs/cloud/location/locations_pb2.pyi
google-stubs/gapic/metadata/__init__.pyi
google-stubs/gapic/metadata/gapic_metadata_pb2.pyi
google-stubs/gapic/metadata/py.typed
google-stubs/logging/type/__init__.pyi
google-stubs/logging/type/http_request_pb2.pyi
google-stubs/logging/type/log_severity_pb2.pyi
google-stubs/logging/type/py.typed
google-stubs/longrunning/__init__.pyi
google-stubs/longrunning/operations_grpc.pyi
google-stubs/longrunning/operations_grpc_pb2.pyi
google-stubs/longrunning/operations_pb2.pyi
google-stubs/longrunning/operations_pb2_grpc.pyi
google-stubs/longrunning/operations_proto.pyi
google-stubs/longrunning/operations_proto_pb2.pyi
google-stubs/longrunning/py.typed
google-stubs/rpc/code_pb2.pyi
googleapis_common_protos_stubs-2.3.0.dist-info/LICENSE
googleapis_common_protos_stubs-2.3.0.dist-info/METADATA
googleapis_common_protos_stubs-2.3.0.dist-info/WHEEL
googleapis_common_protos_stubs-2.3.0.dist-info/RECORD
